README.md
setup.py
sensitive_word.egg-info/PKG-INFO
sensitive_word.egg-info/SOURCES.txt
sensitive_word.egg-info/dependency_links.txt
sensitive_word.egg-info/top_level.txt
textfilter/__init__.py