Metadata-Version: 1.0
Name: sensitive-word
Version: 0.5
Summary: sensitive-word
Home-page: https://github.com/wqfff/sensitiveword.git
Author: wqf
Author-email: UNKNOWN
License: UNKNOWN
Platform: UNKNOWN
